TroxPackage/__init__.py
TroxPackage/code.py
TroxPackage-1.0.dist-info/METADATA
TroxPackage-1.0.dist-info/RECORD
TroxPackage-1.0.dist-info/WHEEL
TroxPackage-1.0.dist-info/top_level.txt
