Metadata-Version: 2.1
Name: TroxPackage
Version: 1.0
Summary: Trox python package
Home-page: https://gitlab.com/ja_Quben/TroxPackage.git
Author: Jakub Zep
Author-email: myemail@example.com
License: MIT
Platform: UNKNOWN
